jupyter_tensorboard_proxy/__init__.py
jupyter_tensorboard_proxy/icons/tensorboard.svg
jupyter_tensorboardproxy_proxy/__init__.py
jupyter_tensorboard_proxy-0.1.1.dist-info/LICENSE
jupyter_tensorboard_proxy-0.1.1.dist-info/METADATA
jupyter_tensorboard_proxy-0.1.1.dist-info/WHEEL
jupyter_tensorboard_proxy-0.1.1.dist-info/entry_points.txt
jupyter_tensorboard_proxy-0.1.1.dist-info/top_level.txt
jupyter_tensorboard_proxy-0.1.1.dist-info/RECORD
