Metadata-Version: 2.1
Name: jupyter-tensorboard-proxy
Version: 0.1.1
Summary: kopkop@gmail.com
Home-page: https://github.com/kopwei/jupyter-tensorboard-proxy
Author: kopkop
License: UNKNOWN
Keywords: jupyter,tensorboard,jupyterhub
Platform: UNKNOWN
Classifier: Framework :: Jupyter
Requires-Dist: jupyter-server-proxy (>=1.5.0)
Requires-Dist: tensorboard (>=2.4.1)
